model2vec/__init__.py
model2vec/hf_utils.py
model2vec/model.py
model2vec/py.typed
model2vec/quantization.py
model2vec/utils.py
model2vec/version.py
model2vec/distill/__init__.py
model2vec/distill/distillation.py
model2vec/distill/inference.py
model2vec/distill/utils.py
model2vec/inference/README.md
model2vec/inference/__init__.py
model2vec/inference/model.py
model2vec/modelcards/classifier_template.md
model2vec/modelcards/model_card_template.md
model2vec/tokenizer/__init__.py
model2vec/tokenizer/datamodels.py
model2vec/tokenizer/model.py
model2vec/tokenizer/normalizer.py
model2vec/tokenizer/pretokenizer.py
model2vec/tokenizer/tokenizer.py
model2vec/train/README.md
model2vec/train/__init__.py
model2vec/train/base.py
model2vec/train/classifier.py
model2vec-0.6.0.dist-info/licenses/LICENSE
model2vec-0.6.0.dist-info/METADATA
model2vec-0.6.0.dist-info/WHEEL
model2vec-0.6.0.dist-info/top_level.txt
model2vec-0.6.0.dist-info/RECORD
