Metadata-Version: 2.4
Name: model2vec
Version: 0.6.0
Summary: Fast State-of-the-Art Static Embeddings
Author-email: Stéphan Tulkens <stephantul@gmail.com>, Thomas van Dongen <thomas123@live.nl>
License: MIT License
Project-URL: Homepage, https://github.com/MinishLab
Project-URL: Bug Reports, https://github.com/MinishLab/model2vec/issues
Project-URL: Source, https://github.com/MinishLab/model2vec
Classifier: Development Status :: 4 - Beta
Classifier: Intended Audience :: Developers
Classifier: Intended Audience :: Science/Research
Classifier: Topic :: Scientific/Engineering :: Artificial Intelligence
Classifier: Topic :: Software Development :: Libraries
Classifier: License :: OSI Approved :: MIT License
Classifier: Programming Language :: Python :: 3 :: Only
Classifier: Programming Language :: Python :: 3.9
Classifier: Programming Language :: Python :: 3.10
Classifier: Programming Language :: Python :: 3.11
Classifier: Programming Language :: Python :: 3.12
Classifier: Natural Language :: English
Requires-Python: >=3.9
License-File: LICENSE
Requires-Dist: jinja2
Requires-Dist: joblib
Requires-Dist: numpy
Requires-Dist: rich
Requires-Dist: safetensors
Requires-Dist: setuptools
Requires-Dist: tokenizers>=0.20
Requires-Dist: tqdm
Provides-Extra: dev
Requires-Dist: black; extra == "dev"
Requires-Dist: ipython; extra == "dev"
Requires-Dist: mypy; extra == "dev"
Requires-Dist: pre-commit; extra == "dev"
Requires-Dist: pytest; extra == "dev"
Requires-Dist: pytest-cov; extra == "dev"
Requires-Dist: ruff; extra == "dev"
Provides-Extra: distill
Requires-Dist: torch; extra == "distill"
Requires-Dist: transformers<=4.52.1; extra == "distill"
Requires-Dist: scikit-learn; extra == "distill"
Provides-Extra: onnx
Requires-Dist: onnx; extra == "onnx"
Requires-Dist: torch; extra == "onnx"
Provides-Extra: train
Requires-Dist: torch; extra == "train"
Requires-Dist: lightning; extra == "train"
Requires-Dist: scikit-learn; extra == "train"
Requires-Dist: skops; extra == "train"
Provides-Extra: inference
Requires-Dist: scikit-learn; extra == "inference"
Requires-Dist: skops; extra == "inference"
Provides-Extra: tokenizer
Requires-Dist: transformers; extra == "tokenizer"
Dynamic: license-file
